mkdocstrings_handlers/shell/__init__.py
mkdocstrings_handlers/shell/_internal/__init__.py
mkdocstrings_handlers/shell/_internal/config.py
mkdocstrings_handlers/shell/_internal/debug.py
mkdocstrings_handlers/shell/_internal/handler.py
mkdocstrings_handlers/shell/config.py
mkdocstrings_handlers/shell/handler.py
mkdocstrings_handlers/shell/py.typed
mkdocstrings_handlers/shell/templates/material/_base/function.html.jinja
mkdocstrings_handlers/shell/templates/material/_base/script.html.jinja
mkdocstrings_handlers/shell/templates/material/function.html.jinja
mkdocstrings_handlers/shell/templates/material/script.html.jinja
mkdocstrings_handlers/shell/templates/material/style.css
mkdocstrings_shell-1.0.4.dist-info/METADATA
mkdocstrings_shell-1.0.4.dist-info/WHEEL
mkdocstrings_shell-1.0.4.dist-info/entry_points.txt
mkdocstrings_shell-1.0.4.dist-info/licenses/LICENSE
mkdocstrings_shell-1.0.4.dist-info/RECORD
