Metadata-Version: 2.4
Name: mkdocstrings-shell
Version: 1.0.4
Summary: A shell scripts/libraries handler for mkdocstrings.
Author-Email: =?utf-8?q?Timoth=C3=A9e_Mazzucotelli?= <dev@pawamoy.fr>
License-Expression: ISC
License-File: LICENSE
Classifier: Development Status :: 4 - Beta
Classifier: Intended Audience :: Developers
Classifier: Programming Language :: Python
Classifier: Programming Language :: Python :: 3
Classifier: Programming Language :: Python :: 3 :: Only
Classifier: Programming Language :: Python :: 3.9
Classifier: Programming Language :: Python :: 3.10
Classifier: Programming Language :: Python :: 3.11
Classifier: Programming Language :: Python :: 3.12
Classifier: Programming Language :: Python :: 3.13
Classifier: Programming Language :: Python :: 3.14
Classifier: Topic :: Documentation
Classifier: Topic :: Software Development
Classifier: Topic :: Utilities
Classifier: Typing :: Typed
Project-URL: Homepage, https://mkdocstrings.github.io/shell
Project-URL: Documentation, https://mkdocstrings.github.io/shell
Project-URL: Changelog, https://mkdocstrings.github.io/shell/changelog
Project-URL: Repository, https://github.com/mkdocstrings/shell
Project-URL: Issues, https://github.com/mkdocstrings/shell/issues
Project-URL: Discussions, https://github.com/mkdocstrings/shell/discussions
Project-URL: Gitter, https://gitter.im/mkdocstrings/shell
Project-URL: Funding, https://github.com/sponsors/pawamoy
Requires-Python: >=3.9
Requires-Dist: mkdocstrings>=0.28.3
Requires-Dist: shellman>=1.0.2
